{
	"info": {
		"_postman_id": "f832f07b-2d23-488a-ae8b-a846b84fc4da",
		"name": "ReadingisGoodApp",
		"schema": "https://schema.getpostman.com/json/collection/v2.1.0/collection.json"
	},
	"item": [
		{
			"name": "Customer",
			"item": [
				{
					"name": "Register new customer",
					"request": {
						"auth": {
							"type": "bearer",
							"bearer": [
								{
									"key": "token",
									"value": "{{token}}",
									"type": "string"
								}
							]
						},
						"method": "POST",
						"header": [],
						"body": {
							"mode": "raw",
							"raw": "{\n    \"firstName\":\"serhat\",\n    \"lastName\":\"yildiz\",\n    \"email\":\"yildiz_serhat@hotmail.com\",\n    \"phone\": 5388297178,\n    \"token\": \"Bearer eyJhbGciOiJIUzUxMiJ9.eyJqdGkiOiJzb2Z0dGVrSldUIiwic3ViIjoieWlsZGl6X3NlcmhhdEBob3RtYWlsLmNvbSIsImF1dGhvcml0aWVzIjpbIlJPTEVfVVNFUiJdLCJpYXQiOjE2MjA1NTc1OTMsImV4cCI6MTYyMDU1ODE5M30.qPcE9mlCUhCmygnQgJf7_2lg5ZCsPGMLMZS5fldbtxqEr5UKmY_NkXXc2m1mKjFQxhryA_HD26VdNxJ4dFugVQ\"\n}\n\n",
							"options": {
								"raw": {
									"language": "json"
								}
							}
						},
						"url": {
							"raw": "{{base_url}}/customers",
							"host": [
								"{{base_url}}"
							],
							"path": [
								"customers"
							]
						}
					},
					"response": []
				},
				{
					"name": "Get Customers",
					"request": {
						"auth": {
							"type": "bearer",
							"bearer": [
								{
									"key": "token",
									"value": "{{token}}",
									"type": "string"
								}
							]
						},
						"method": "GET",
						"header": [],
						"url": {
							"raw": "{{base_url}}/customers",
							"host": [
								"{{base_url}}"
							],
							"path": [
								"customers"
							]
						}
					},
					"response": []
				},
				{
					"name": "Delete customer",
					"request": {
						"auth": {
							"type": "bearer",
							"bearer": [
								{
									"key": "token",
									"value": "{{token}}",
									"type": "string"
								}
							]
						},
						"method": "DELETE",
						"header": [],
						"url": {
							"raw": "{{base_url}}/customers/1",
							"host": [
								"{{base_url}}"
							],
							"path": [
								"customers",
								"1"
							]
						}
					},
					"response": []
				}
			],
			"auth": {
				"type": "bearer",
				"bearer": [
					{
						"key": "token",
						"value": "{{token}}",
						"type": "string"
					}
				]
			},
			"event": [
				{
					"listen": "prerequest",
					"script": {
						"type": "text/javascript",
						"exec": [
							""
						]
					}
				},
				{
					"listen": "test",
					"script": {
						"type": "text/javascript",
						"exec": [
							""
						]
					}
				}
			]
		},
		{
			"name": "Orders",
			"item": [
				{
					"name": "PlaceOrder",
					"event": [
						{
							"listen": "test",
							"script": {
								"exec": [
									"var jsonData = JSON.parse(responseBody);",
									"pm.collectionVariables.set(\"orderTrackingNumber\", jsonData['orderTrackingNumber']);"
								],
								"type": "text/javascript"
							}
						}
					],
					"request": {
						"auth": {
							"type": "bearer",
							"bearer": [
								{
									"key": "token",
									"value": "{{token}}",
									"type": "string"
								}
							]
						},
						"method": "POST",
						"header": [],
						"body": {
							"mode": "raw",
							"raw": "{\n   \"customer\":{\n      \"firstName\":\"serhat\",\n      \"lastName\":\"yildiz\",\n      \"email\":\"yildiz_serhat@hotmail.com\"\n   },\n   \"shippingAddress\":{\n      \"street\":\"afasa\",\n      \"city\":\"afasa\",\n      \"state\":\"Alberta\",\n      \"country\":\"Canada\",\n      \"zipCode\":\"afasa\"\n   },\n   \"billingAddress\":{\n      \"street\":\"fsfsf\",\n      \"city\":\"sfdsf\",\n      \"state\":\"Acre\",\n      \"country\":\"Brazil\",\n      \"zipCode\":\"19111\"\n   },\n   \"order\":{\n      \"totalPrice\":36.98,\n      \"totalQuantity\":20\n   },\n   \"orderItems\":[\n      {\n         \"quantity\":10,\n         \"unitPrice\":29.99,\n         \"productId\":1\n      },\n      {\n         \"quantity\":10,\n         \"unitPrice\":69.99,\n         \"productId\":2\n      }\n   ]\n}",
							"options": {
								"raw": {
									"language": "json"
								}
							}
						},
						"url": {
							"raw": "{{base_url}}/checkout/purchase",
							"host": [
								"{{base_url}}"
							],
							"path": [
								"checkout",
								"purchase"
							]
						}
					},
					"response": []
				},
				{
					"name": "GetDetailedOrderInfoByEmail Copy",
					"request": {
						"auth": {
							"type": "bearer",
							"bearer": [
								{
									"key": "token",
									"value": "{{token}}",
									"type": "string"
								}
							]
						},
						"method": "GET",
						"header": [],
						"url": {
							"raw": "{{base_url}}/orders/search/findByOrderTrackingNumber?trackingNumber={{orderTrackingNumber}}",
							"host": [
								"{{base_url}}"
							],
							"path": [
								"orders",
								"search",
								"findByOrderTrackingNumber"
							],
							"query": [
								{
									"key": "trackingNumber",
									"value": "{{orderTrackingNumber}}"
								}
							]
						}
					},
					"response": []
				},
				{
					"name": "GetOrderByEmail",
					"request": {
						"auth": {
							"type": "bearer",
							"bearer": [
								{
									"key": "token",
									"value": "{{token}}",
									"type": "string"
								}
							]
						},
						"method": "GET",
						"header": [],
						"url": {
							"raw": "{{base_url}}/order/yildiz_serhat@hotmail.com",
							"host": [
								"{{base_url}}"
							],
							"path": [
								"order",
								"yildiz_serhat@hotmail.com"
							]
						}
					},
					"response": []
				}
			],
			"auth": {
				"type": "bearer",
				"bearer": [
					{
						"key": "token",
						"value": "{{token}}",
						"type": "string"
					}
				]
			},
			"event": [
				{
					"listen": "prerequest",
					"script": {
						"type": "text/javascript",
						"exec": [
							""
						]
					}
				},
				{
					"listen": "test",
					"script": {
						"type": "text/javascript",
						"exec": [
							""
						]
					}
				}
			]
		},
		{
			"name": "Product",
			"item": [
				{
					"name": "GetProductsAndStocks",
					"request": {
						"auth": {
							"type": "bearer",
							"bearer": [
								{
									"key": "token",
									"value": "{{token}}",
									"type": "string"
								}
							]
						},
						"method": "GET",
						"header": [],
						"url": {
							"raw": "{{base_url}}/products",
							"host": [
								"{{base_url}}"
							],
							"path": [
								"products"
							],
							"query": [
								{
									"key": "user",
									"value": "user",
									"disabled": true
								},
								{
									"key": "password",
									"value": "password",
									"disabled": true
								}
							]
						}
					},
					"response": []
				}
			],
			"auth": {
				"type": "bearer",
				"bearer": [
					{
						"key": "token",
						"value": "{{token}}",
						"type": "string"
					}
				]
			},
			"event": [
				{
					"listen": "prerequest",
					"script": {
						"type": "text/javascript",
						"exec": [
							""
						]
					}
				},
				{
					"listen": "test",
					"script": {
						"type": "text/javascript",
						"exec": [
							""
						]
					}
				}
			]
		},
		{
			"name": "Login",
			"item": [
				{
					"name": "Login",
					"event": [
						{
							"listen": "test",
							"script": {
								"exec": [
									"var jsonData = JSON.parse(responseBody);",
									"pm.collectionVariables.set(\"token\", jsonData['token']);"
								],
								"type": "text/javascript"
							}
						}
					],
					"request": {
						"auth": {
							"type": "noauth"
						},
						"method": "POST",
						"header": [],
						"body": {
							"mode": "urlencoded",
							"urlencoded": [
								{
									"key": "email",
									"value": "yildiz_serhat@hotmail.com",
									"type": "text"
								},
								{
									"key": "password",
									"value": "213231",
									"type": "text"
								}
							]
						},
						"url": {
							"raw": "http://localhost:8080/login",
							"protocol": "http",
							"host": [
								"localhost"
							],
							"port": "8080",
							"path": [
								"login"
							]
						}
					},
					"response": []
				},
				{
					"name": "Api-doc",
					"request": {
						"auth": {
							"type": "bearer",
							"bearer": [
								{
									"key": "token",
									"value": "{{token}}",
									"type": "string"
								}
							]
						},
						"method": "GET",
						"header": [],
						"url": {
							"raw": "http://localhost:8080/api-docs",
							"protocol": "http",
							"host": [
								"localhost"
							],
							"port": "8080",
							"path": [
								"api-docs"
							]
						}
					},
					"response": []
				}
			],
			"auth": {
				"type": "bearer",
				"bearer": [
					{
						"key": "token",
						"value": "{{token}}",
						"type": "string"
					}
				]
			},
			"event": [
				{
					"listen": "prerequest",
					"script": {
						"type": "text/javascript",
						"exec": [
							""
						]
					}
				},
				{
					"listen": "test",
					"script": {
						"type": "text/javascript",
						"exec": [
							""
						]
					}
				}
			]
		}
	],
	"auth": {
		"type": "bearer",
		"bearer": [
			{
				"key": "token",
				"value": "{{token}}",
				"type": "string"
			}
		]
	},
	"event": [
		{
			"listen": "prerequest",
			"script": {
				"type": "text/javascript",
				"exec": [
					""
				]
			}
		},
		{
			"listen": "test",
			"script": {
				"type": "text/javascript",
				"exec": [
					""
				]
			}
		}
	],
	"variable": [
		{
			"key": "base_url",
			"value": "http://localhost:8080/api"
		},
		{
			"key": "token",
			"value": ""
		},
		{
			"key": "orderTrackingNumber",
			"value": ""
		}
	]
}